iam_validation/__init__.py
iam_validation/dims.py
iam_validation/pdhelpers.py
iam_validation/pyam_helpers.py
iam_validation/type_helpers.py
iam_validation/criteria/__init__.py
iam_validation/criteria/timeseries_criteria_core.py
iam_validation/nomenclature/__init__.py
iam_validation/nomenclature/default_definitions.py
iam_validation/nomenclature/defs.py
iam_validation/nomenclature/mapping.py
iam_validation/nomenclature/multi_load.py
iam_validation/nomenclature/validation.py
iam_validation/output/__init__.py
iam_validation/output/base.py
iam_validation/output/column_names.py
iam_validation/output/excel.py
iam_validation/output/timeseries.py
iam_validation/output/styling/__init__.py
iam_validation/output/styling/base.py
iam_validation/targets/__init__.py
iam_validation/targets/ar6_vetting_targets.py
iam_validation/targets/target_classes.py
iam_validation-0.1.1.dist-info/METADATA
iam_validation-0.1.1.dist-info/WHEEL
iam_validation-0.1.1.dist-info/licenses/LICENSE
iam_validation-0.1.1.dist-info/RECORD
