Metadata-Version: 2.3
Name: iam-validation
Version: 0.1.1
Summary: Validation of names and values in IAMC-formatted model output against definitions and reference targets
Project-URL: Repository, https://github.com/ciceroOslo/iam-validation
Project-URL: Issues, https://github.com/ciceroOslo/iam-validation/issues
Author-email: Jan Ivar Korsbakken <janko@cicero.oslo.no>
License: Apache-2.0
License-File: LICENSE
Requires-Python: >=3.11
Requires-Dist: nomenclature-iamc>=0.20
Requires-Dist: pandas-indexing>=0.5.2
Requires-Dist: pathways-ensemble-analysis>=1.0
Requires-Dist: pyam-iamc>=2.3
Requires-Dist: pyyaml>=6.0.2
Requires-Dist: xlsxwriter>=3.2.0
